[
    {
        "date": "2024-01-15",
        "title": "Senior Software Engineer",
        "organization": "PNC Bank",
        "description": "Promoted to Senior Software Engineer, leading development of internal tooling and cloud infrastructure projects.",
        "icon": "fas fa-briefcase"
    },
    {
        "date": "2023-06-01",
        "title": "Cloud Migration Project",
        "organization": "PNC Bank",
        "description": "Led the migration of legacy services to AWS, reducing infrastructure costs and improving deployment speed.",
        "icon": "fas fa-cloud"
    },
    {
        "date": "2022-08-20",
        "title": "Software Engineer",
        "organization": "PNC Bank",
        "description": "Joined PNC Bank as a Software Engineer, working on full-stack development with modern web technologies.",
        "icon": "fas fa-code"
    },
    {
        "date": "2022-05-15",
        "title": "Bachelor of Science in Computer Science",
        "organization": "University of Pittsburgh",
        "description": "Graduated with a degree in Computer Science, focusing on software engineering and distributed systems.",
        "icon": "fas fa-graduation-cap"
    }
]
